README.rst
requirements.txt
setup.py
apirequests/__init__.py
apirequests.egg-info/PKG-INFO
apirequests.egg-info/SOURCES.txt
apirequests.egg-info/dependency_links.txt
apirequests.egg-info/requires.txt
apirequests.egg-info/top_level.txt