Metadata-Version: 1.0
Name: apirequests
Version: 0.0.7
Summary: HTTP client built around "requests" library
Home-page: https://github.com/alexandr-san4ez/apirequests
Author: san4ez
Author-email: UNKNOWN
License: MIT
Keywords: HTTP API REST HTTP-client requests
Platform: UNKNOWN
